MANIFEST.in
README.rst
setup.cfg
setup.py
zapcli/__init__.py
zapcli/cli.py
zapcli/exceptions.py
zapcli/helpers.py
zapcli/log.py
zapcli/zap_helper.py
zapcli.egg-info/PKG-INFO
zapcli.egg-info/SOURCES.txt
zapcli.egg-info/dependency_links.txt
zapcli.egg-info/entry_points.txt
zapcli.egg-info/requires.txt
zapcli.egg-info/top_level.txt
zapcli/commands/__init__.py
zapcli/commands/context.py
zapcli/commands/policies.py
zapcli/commands/scanners.py
zapcli/commands/scripts.py
zapcli/commands/session.py