Metadata-Version: 1.1
Name: zapcli
Version: 0.10.0
Summary: A ZAP CLI tool for targeted tests from the command line.
Home-page: https://github.com/Grunny/zap-cli
Author: Daniel Grunwell (grunny)
Author-email: mwgrunny@gmail.com
License: MIT
Platform: UNKNOWN
Classifier: Topic :: Security
Classifier: Topic :: Software Development :: Quality Assurance
Classifier: Topic :: Software Development :: Testing
Classifier: Topic :: Software Development :: Libraries :: Python Modules
Classifier: Intended Audience :: Developers
Classifier: Intended Audience :: Information Technology
